common/__init__.py
common/pfpy_common_exception.py
objman/__init__.py
objman/copy_object.py
objman/object_instanceof.py
pf_py_object_man-1.1.dist-info/LICENSE
pf_py_object_man-1.1.dist-info/METADATA
pf_py_object_man-1.1.dist-info/WHEEL
pf_py_object_man-1.1.dist-info/top_level.txt
pf_py_object_man-1.1.dist-info/RECORD
