Metadata-Version: 2.1
Name: pf-py-object-man
Version: 1.1
Summary: Problem Fighter Python Object Manager
Home-page: https://github.com/problemfighter/pf-py-object-man
Author: Touhid Mia
Author-email: hmtm.cse@gmail.com
License: Apache 2.0
Platform: any
Classifier: Environment :: Web Environment
Classifier: Intended Audience :: Developers
Classifier: License :: OSI Approved :: Apache Software License
Classifier: Operating System :: OS Independent
Classifier: Programming Language :: Python
Classifier: Topic :: Internet :: WWW/HTTP :: Dynamic Content
Classifier: Topic :: Software Development :: Libraries :: Python Modules
